mdpo_llm/__init__.py
mdpo_llm/language.py
mdpo_llm/llm_interface.py
mdpo_llm/manager.py
mdpo_llm/parser.py
mdpo_llm/processor.py
mdpo_llm/prompts.py
mdpo_llm/reconstructor.py
mdpo_llm-0.1.0.dist-info/METADATA
mdpo_llm-0.1.0.dist-info/WHEEL
mdpo_llm-0.1.0.dist-info/licenses/LICENSE
mdpo_llm-0.1.0.dist-info/RECORD
