Metadata-Version: 2.4
Name: mdpo-llm
Version: 0.1.0
Summary: Process Markdown documents with LLMs using PO files for efficient translation and refinement
Project-URL: Homepage, https://github.com/willy/mdpo-llm
Project-URL: Documentation, https://github.com/willy/mdpo-llm#readme
Project-URL: Repository, https://github.com/willy/mdpo-llm.git
Project-URL: Issues, https://github.com/willy/mdpo-llm/issues
Author-email: Will Kang <willysk73@outlook.com>
License: MIT
License-File: LICENSE
Keywords: document-processing,gettext,i18n,llm,localization,markdown,po,translation
Classifier: Development Status :: 3 - Alpha
Classifier: Intended Audience :: Developers
Classifier: License :: OSI Approved :: MIT License
Classifier: Operating System :: OS Independent
Classifier: Programming Language :: Python :: 3
Classifier: Programming Language :: Python :: 3.10
Classifier: Programming Language :: Python :: 3.11
Classifier: Programming Language :: Python :: 3.12
Classifier: Topic :: Software Development :: Libraries :: Python Modules
Classifier: Topic :: Text Processing :: Linguistic
Classifier: Topic :: Text Processing :: Markup :: Markdown
Requires-Python: >=3.10
Requires-Dist: polib>=1.2.0
